Espalier/ARGBuilder.py
Espalier/ARGSampler.py
Espalier/ARGSeqSimulator.py
Espalier/ARGSimulator.py
Espalier/ARGweaver.py
Espalier/Dendro2TSConverter.py
Espalier/IQTree.py
Espalier/MAF.py
Espalier/PlotARGPerformance.py
Espalier/PlotDistRegression.py
Espalier/PlotEstimateRegression.py
Espalier/PlotMAFPerformance.py
Espalier/PlotTanglegrams.py
Espalier/RAxML.py
Espalier/Reconciler.py
Espalier/SCARLikelihood.py
Espalier/SCARLikelihoodStrict.py
Espalier/TreeDisentagler.py
Espalier/TreeOps.py
Espalier/TreeRandomizer.py
Espalier/TreeReconciler.py
Espalier/Utils.py
Espalier/Viterbi.py
Espalier/__init__.py
Espalier/balticmod.py
Espalier/concat_alignments.py
Espalier/defunct_MAF.py
Espalier/espalier.py
Espalier/poty_ARG.py
Espalier/test_ARG_sampler.py
Espalier/test_EM_estimator.py
Espalier/sim/ARGSimulator.py
Espalier/sim/ARGweaver.py
Espalier/sim/TreeRandomizer.py
Espalier/sim/__init__.py
Espalier/tests/__init__.py
Espalier/tests/profile_MAFs.py
Espalier/tests/test_ARG_reconstruction.py
Espalier/tests/test_EM_estimator.py
Espalier/tests/test_core.py
Espalier/tests/test_deep_rooting.py
Espalier/tests/test_dendro2ts_conversion.py
Espalier/tests/test_maf.py
Espalier/tests/test_maf_randomSPR.py
Espalier/tests/test_msprime_sims.py
Espalier/tests/test_recomb_placement.py
Espalier/tests/test_recomb_placement_path.py
Espalier/tests/test_reconciled_linked_heights.py
Espalier/tests/test_reconciler_randomSPR.py
Espalier/viz/PlotTanglegrams.py
Espalier/viz/TreePlotter.py
Espalier/viz/__init__.py
Espalier/viz/balticmod.py
Espalier-0.1.2.dist-info/METADATA
Espalier-0.1.2.dist-info/WHEEL
Espalier-0.1.2.dist-info/entry_points.txt
Espalier-0.1.2.dist-info/top_level.txt
Espalier-0.1.2.dist-info/RECORD
