Metadata-Version: 2.1
Name: Espalier
Version: 0.1.2
Summary: Espalier is a Python package for working with discordant phylogenetic trees using maximum agreement forests
Home-page: https://github.com/davidrasm/Espalier
Author: David Rasmussen
Author-email: drasmus@ncsu.edu
License: Apache License 2.0
Platform: UNKNOWN
Requires-Dist: numpy
Requires-Dist: dendropy
Requires-Dist: pandas
Requires-Dist: tskit
Requires-Dist: biopython
Requires-Dist: scipy
Requires-Dist: click
